BossWeb/App.py
BossWeb/__init__.py
BossWeb/main.py
bossweb-0.0.2.dist-info/LICENSE
bossweb-0.0.2.dist-info/METADATA
bossweb-0.0.2.dist-info/WHEEL
bossweb-0.0.2.dist-info/entry_points.txt
bossweb-0.0.2.dist-info/top_level.txt
bossweb-0.0.2.dist-info/RECORD
