Metadata-Version: 2.1
Name: bossweb
Version: 0.0.2
Summary: GUI framework to develop web and desktop apps in pure python using html, css and scripting. Powered by PyQt5, flask, Brython, selenium and libsass
Home-page: https://github.com/atharva-naik/BossWeb
Author: Atharva Naik
Author-email: atharvanaik2018@gmail.com
License: GPL
Platform: UNKNOWN
Classifier: License :: OSI Approved :: GNU General Public License (GPL)
Classifier: Programming Language :: Python :: 3
Classifier: Programming Language :: Python :: 3.7
Requires-Dist: bs4
Requires-Dist: flask
Requires-Dist: PyQt5
Requires-Dist: brython
Requires-Dist: libsass
Requires-Dist: selenium
Requires-Dist: PyQtWebEngine
